cycling_cadence_display/__init__.py
cycling_cadence_display/app.py
cycling_cadence_display/test_app.py
cycling_cadence_display-0.1.0.dist-info/METADATA
cycling_cadence_display-0.1.0.dist-info/WHEEL
cycling_cadence_display-0.1.0.dist-info/entry_points.txt
cycling_cadence_display-0.1.0.dist-info/top_level.txt
cycling_cadence_display-0.1.0.dist-info/RECORD
