Metadata-Version: 2.1
Name: cycling-cadence-display
Version: 0.1.0
Summary: A terminal-user-interface to display a dashboard of information about a cycling cadence meter via Bluetooth
Home-page: https://github.com/cboddy/cycling-cadence-display
Author: Chris Boddy
Author-email: chris@boddy.im
License: UNKNOWN
Platform: UNKNOWN
Requires-Dist: bleak
Requires-Dist: pandas
Requires-Dist: pycycling
Requires-Dist: rich
Requires-Dist: termplotlib
